AUTHORS
CHANGELOG.txt
DESCRIPTION
LICENSE
MANIFEST.in
README.rst
setup.py
development_fabfile/__init__.py
development_fabfile/fabfile/__init__.py
development_fabfile/fabfile/fabfile_settings.py.digital_ocean.sample
development_fabfile/fabfile/fabfile_settings.py.sample
development_fabfile/fabfile/local.py
development_fabfile/fabfile/remote.py
development_fabfile/fabfile/servers.py
development_fabfile/fabfile/utils.py
development_fabfile/tests/__init__.py
development_fabfile/tests/local_tests.py
development_fabfile/tests/settings.py
django_development_fabfile.egg-info/PKG-INFO
django_development_fabfile.egg-info/SOURCES.txt
django_development_fabfile.egg-info/dependency_links.txt
django_development_fabfile.egg-info/requires.txt
django_development_fabfile.egg-info/top_level.txt