Metadata-Version: 1.0
Name: django-development-fabfile
Version: 2.14.6
Summary: A fabfile to ease many tasks during development and deployment of Django projects.
